xontrib/dalias/__init__.py
xontrib/dalias/to_dict.py
xontrib_dalias-0.0.6.dist-info/LICENSE
xontrib_dalias-0.0.6.dist-info/METADATA
xontrib_dalias-0.0.6.dist-info/WHEEL
xontrib_dalias-0.0.6.dist-info/top_level.txt
xontrib_dalias-0.0.6.dist-info/RECORD
